binhd/__init__.py
binhd/classifiers.py
binhd/embeddings.py
binhd/functional.py
binhd/datasets/__init__.py
binhd/datasets/adult.py
binhd/datasets/dataset.py
binhd/datasets/iris.py
binhd/datasets/statlog.py
binhd-1.0.0a0.dist-info/LICENSE
binhd-1.0.0a0.dist-info/METADATA
binhd-1.0.0a0.dist-info/WHEEL
binhd-1.0.0a0.dist-info/top_level.txt
binhd-1.0.0a0.dist-info/RECORD
