Metadata-Version: 2.2
Name: binhd
Version: 1.0.0a0
Summary: BinHD is a Python implementation based on A Binary Learning Framework for Hyperdimensional Computing
Home-page: https://github.com/leandro-santiago/binhd
Author: Leandro Santiago de Araújo
License: MIT
License-File: LICENSE
Requires-Dist: torch-hd
Requires-Dist: ucimlrepo
Requires-Dist: pandas
Dynamic: author
Dynamic: description
Dynamic: description-content-type
Dynamic: home-page
Dynamic: license
Dynamic: requires-dist
Dynamic: summary
